thlink_backend_object_storage_lib/__init__.py
thlink_backend_object_storage_lib/object_storage.py
thlink_backend_object_storage_lib-0.2.2.dist-info/LICENSE
thlink_backend_object_storage_lib-0.2.2.dist-info/WHEEL
thlink_backend_object_storage_lib-0.2.2.dist-info/METADATA
thlink_backend_object_storage_lib-0.2.2.dist-info/RECORD
