Metadata-Version: 2.1
Name: thlink-backend-object-storage-lib
Version: 0.2.2
Summary: S3 Wrapper
Author: thlink
Requires-Python: >=3.7,<4.0
Classifier: Programming Language :: Python :: 3
Classifier: Programming Language :: Python :: 3.7
Classifier: Programming Language :: Python :: 3.8
Classifier: Programming Language :: Python :: 3.9
Requires-Dist: boto3 (>=1.17.78,<2.0.0)
